credentials_manager_client/__init__.py
credentials_manager_client/app.py
credentials_manager_client/main.py
credentials_manager_client/apps/__init__.py
credentials_manager_client/apps/auth/__init__.py
credentials_manager_client/apps/auth/abstract_models.py
credentials_manager_client/apps/auth/models.py
credentials_manager_client/db/__init__.py
credentials_manager_client/db/base_model.py
credentials_manager_client-0.0.1.dist-info/LICENSE
credentials_manager_client-0.0.1.dist-info/METADATA
credentials_manager_client-0.0.1.dist-info/WHEEL
credentials_manager_client-0.0.1.dist-info/entry_points.txt
credentials_manager_client-0.0.1.dist-info/top_level.txt
credentials_manager_client-0.0.1.dist-info/RECORD
