Metadata-Version: 2.1
Name: credentials-manager-client
Version: 0.0.1
Summary: Provide credentials for services
Home-page: https://github.com/makersdevs/credentials_manager
Author-email: Makers <makerskg@gmail.com>
License: The MIT License (MIT)
Project-URL: Homepage, https://github.com/makersdevs/credentials_manager
Keywords: credentials-manager-client,cred-manager-client
Classifier: License :: OSI Approved :: MIT License
Classifier: Programming Language :: Python
Classifier: Programming Language :: Python :: 3
Requires-Python: >=3.10.3
License-File: LICENSE
Requires-Dist: pydantic (>=1.9.2)
Requires-Dist: environs (>=9.5.0)
Requires-Dist: psutil (>=5.9.4)
Requires-Dist: tomli ; python_version < "3.11"
Provides-Extra: dev
Requires-Dist: black ; extra == 'dev'
Requires-Dist: bumpver ; extra == 'dev'
Requires-Dist: isort ; extra == 'dev'
Requires-Dist: pip-tools ; extra == 'dev'
Requires-Dist: pytest ; extra == 'dev'
